<annotation>
	<folder>images</folder>
	<filename>bamboo156.png</filename>
	<path>/Users/laraellentuck/Desktop/object-detection/images/bamboo156.png</path>
	<source>
		<database>Unknown</database>
	</source>
	<size>
		<width>2156</width>
		<height>1328</height>
		<depth>3</depth>
	</size>
	<segmented>0</segmented>
	<object>
		<name>bamboo</name>
		<pose>Unspecified</pose>
		<truncated>0</truncated>
		<difficult>0</difficult>
		<bndbox>
			<xmin>49</xmin>
			<ymin>39</ymin>
			<xmax>911</xmax>
			<ymax>1225</ymax>
		</bndbox>
	</object>
	<object>
		<name>bamboo</name>
		<pose>Unspecified</pose>
		<truncated>0</truncated>
		<difficult>0</difficult>
		<bndbox>
			<xmin>949</xmin>
			<ymin>68</ymin>
			<xmax>1502</xmax>
			<ymax>1149</ymax>
		</bndbox>
	</object>
	<object>
		<name>bamboo</name>
		<pose>Unspecified</pose>
		<truncated>1</truncated>
		<difficult>0</difficult>
		<bndbox>
			<xmin>1511</xmin>
			<ymin>120</ymin>
			<xmax>2156</xmax>
			<ymax>1126</ymax>
		</bndbox>
	</object>
</annotation>
