<annotation>
	<folder>New Bamboo</folder>
	<filename>bamboo121.jpg</filename>
	<path>/Users/laraellentuck/Desktop/New Bamboo/bamboo121.jpg</path>
	<source>
		<database>Unknown</database>
	</source>
	<size>
		<width>264</width>
		<height>191</height>
		<depth>3</depth>
	</size>
	<segmented>0</segmented>
	<object>
		<name>bamboo</name>
		<pose>Unspecified</pose>
		<truncated>1</truncated>
		<difficult>0</difficult>
		<bndbox>
			<xmin>41</xmin>
			<ymin>1</ymin>
			<xmax>147</xmax>
			<ymax>132</ymax>
		</bndbox>
	</object>
	<object>
		<name>bamboo</name>
		<pose>Unspecified</pose>
		<truncated>1</truncated>
		<difficult>0</difficult>
		<bndbox>
			<xmin>139</xmin>
			<ymin>1</ymin>
			<xmax>162</xmax>
			<ymax>150</ymax>
		</bndbox>
	</object>
	<object>
		<name>bamboo</name>
		<pose>Unspecified</pose>
		<truncated>1</truncated>
		<difficult>0</difficult>
		<bndbox>
			<xmin>110</xmin>
			<ymin>1</ymin>
			<xmax>139</xmax>
			<ymax>133</ymax>
		</bndbox>
	</object>
	<object>
		<name>bamboo</name>
		<pose>Unspecified</pose>
		<truncated>0</truncated>
		<difficult>0</difficult>
		<bndbox>
			<xmin>55</xmin>
			<ymin>4</ymin>
			<xmax>113</xmax>
			<ymax>104</ymax>
		</bndbox>
	</object>
</annotation>
